{
  "project_info": {
    "project_number": "959139322794",
    "project_id": "demoproject-e222f",
    "storage_bucket": "demoproject-e222f.appspot.com"
  },
  "client": [
    {
      "client_info": {
        "mobilesdk_app_id": "1:959139322794:android:fcc12631f615aa888fa9d3",
        "android_client_info": {
          "package_name": "com.example.demoproject"
        }
      },
      "oauth_client": [],
      "api_key": [
        {
          "current_key": "AIzaSyClo6fqQJY8x9b1hjCsKllTlqyCLlIL990"
        }
      ],
      "services": {
        "appinvite_service": {
          "other_platform_oauth_client": []
        }
      }
    },
    {
      "client_info": {
        "mobilesdk_app_id": "1:959139322794:android:d9274fb6e080488d8fa9d3",
        "android_client_info": {
          "package_name": "com.example.todo_app"
        }
      },
      "oauth_client": [],
      "api_key": [
        {
          "current_key": "AIzaSyClo6fqQJY8x9b1hjCsKllTlqyCLlIL990"
        }
      ],
      "services": {
        "appinvite_service": {
          "other_platform_oauth_client": []
        }
      }
    }
  ],
  "configuration_version": "1"
}